logger_maoze/__init__.py
logger_maoze/logger.py
logger_maoze-0.0.6.dist-info/licenses/LICENSE
logger_maoze-0.0.6.dist-info/WHEEL
logger_maoze-0.0.6.dist-info/METADATA
logger_maoze-0.0.6.dist-info/RECORD
