Metadata-Version: 2.4
Name: logger_maoze
Version: 0.0.6
Summary: A python logger extension package
Author: maoze
Author-email: maoze <moritz.m.steffl@gmail.com>
License-Expression: MIT
License-File: LICENSE
Classifier: Programming Language :: Python :: 3
Classifier: License :: OSI Approved :: MIT License
Classifier: Operating System :: OS Independent
Requires-Python: >=3.12
Project-URL: Homepage, https://github.com/
Project-URL: Issues, https://github.com/
